cleaner/__init__.py
cleaner/access_cleaner.py
cleaner/cleaner.py
cleaner/csv_cleaner.py
cleaner/excel_cleaner.py
cleaner/json_cleaner.py
cleaner/show_matches.py
cleaner/tsv_cleaner.py
github/__init__.py
github/github.py
local/__init__.py
local/local.py
reader/__init__.py
reader/access_reader.py
reader/columns_reader.py
reader/csv_reader.py
reader/excel_reader.py
reader/headers_reader.py
reader/json_reader.py
reader/reader.py
reader/tsv_reader.py
renderer/__init__.py
renderer/renderer.py
sensitibot/__init__.py
sensitibot/__main__.py
sensitibot/custom_formatters.py
sensitibot/parser.py
sensitibot/sensitibot.py
sensitibot-1.1.1.dist-info/entry_points.txt
sensitibot-1.1.1.dist-info/METADATA
sensitibot-1.1.1.dist-info/WHEEL
sensitibot-1.1.1.dist-info/RECORD
